MANIFEST.in
setup.cfg
setup.py
djangomaat/__init__.py
djangomaat/exceptions.py
djangomaat/handlers.py
djangomaat/models.py
djangomaat/register.py
djangomaat/settings.py
djangomaat/tests.py
djangomaat/utils.py
djangomaat.egg-info/PKG-INFO
djangomaat.egg-info/SOURCES.txt
djangomaat.egg-info/dependency_links.txt
djangomaat.egg-info/top_level.txt
djangomaat/__pycache__/__init__.cpython-32.pyc
djangomaat/__pycache__/__init__.cpython-33.pyc
djangomaat/__pycache__/__init__.cpython-34.pyc
djangomaat/__pycache__/exceptions.cpython-32.pyc
djangomaat/__pycache__/exceptions.cpython-33.pyc
djangomaat/__pycache__/exceptions.cpython-34.pyc
djangomaat/__pycache__/handlers.cpython-32.pyc
djangomaat/__pycache__/handlers.cpython-33.pyc
djangomaat/__pycache__/handlers.cpython-34.pyc
djangomaat/__pycache__/models.cpython-32.pyc
djangomaat/__pycache__/models.cpython-33.pyc
djangomaat/__pycache__/models.cpython-34.pyc
djangomaat/__pycache__/register.cpython-32.pyc
djangomaat/__pycache__/register.cpython-33.pyc
djangomaat/__pycache__/register.cpython-34.pyc
djangomaat/__pycache__/settings.cpython-32.pyc
djangomaat/__pycache__/settings.cpython-33.pyc
djangomaat/__pycache__/settings.cpython-34.pyc
djangomaat/__pycache__/tests.cpython-32.pyc
djangomaat/__pycache__/tests.cpython-33.pyc
djangomaat/__pycache__/tests.cpython-34.pyc
djangomaat/__pycache__/utils.cpython-32.pyc
djangomaat/__pycache__/utils.cpython-33.pyc
djangomaat/__pycache__/utils.cpython-34.pyc
djangomaat/management/__init__.py
djangomaat/management/__pycache__/__init__.cpython-32.pyc
djangomaat/management/__pycache__/__init__.cpython-33.pyc
djangomaat/management/__pycache__/__init__.cpython-34.pyc
djangomaat/management/commands/__init__.py
djangomaat/management/commands/maat_show_register.py
djangomaat/management/commands/populate_maat_ranking.py
djangomaat/migrations/0001_initial.py
djangomaat/migrations/__init__.py